<profile>

<ReportVersion>
<Version>2024.1</Version>
</ReportVersion>

<UserAssignments>
<unit>ns</unit>
<ProductFamily>zynquplus</ProductFamily>
<Part>xczu3eg-sfvc784-1-e</Part>
<TopModelName>backProp_64_8_8_Pipeline_VITIS_LOOP_40_1_VITIS_LOOP_41_2</TopModelName>
<TargetClockPeriod>10.00</TargetClockPeriod>
<ClockUncertainty>2.00</ClockUncertainty>
<FlowTarget>vivado</FlowTarget>
</UserAssignments>

<PerformanceEstimates>
<PipelineType>loop auto-rewind stp(delay=0 clock cycles(s))</PipelineType>
<SummaryOfTimingAnalysis>
<unit>ns</unit>
<EstimatedClockPeriod>4.730</EstimatedClockPeriod>
</SummaryOfTimingAnalysis>
<SummaryOfOverallLatency>
<unit>clock cycles</unit>
<Best-caseLatency>66</Best-caseLatency>
<Average-caseLatency>66</Average-caseLatency>
<Worst-caseLatency>66</Worst-caseLatency>
<Best-caseRealTimeLatency>0.660 us</Best-caseRealTimeLatency>
<Average-caseRealTimeLatency>0.660 us</Average-caseRealTimeLatency>
<Worst-caseRealTimeLatency>0.660 us</Worst-caseRealTimeLatency>
<Interval-min>65</Interval-min>
<Interval-max>65</Interval-max>
</SummaryOfOverallLatency>
<SummaryOfLoopLatency>
<VITIS_LOOP_40_1_VITIS_LOOP_41_2>
<Slack>8.00</Slack>
<TripCount>64</TripCount>
<Latency>64</Latency>
<AbsoluteTimeLatency>640</AbsoluteTimeLatency>
<PipelineII>1</PipelineII>
<PipelineDepth>1</PipelineDepth>
<InstanceList>
</InstanceList>
</VITIS_LOOP_40_1_VITIS_LOOP_41_2>
</SummaryOfLoopLatency>
<SummaryOfViolations>
<IssueType>-</IssueType>
<ViolationType>-</ViolationType>
<SourceLocation>C:/Xilinx/Vitis_HLS/2024.1/tps/mingw/8.3.0/win64.o/nt\lib\gcc\x86_64-w64-mingw32\8.3.0\include\c++\array:55~C:/Xilinx/Vitis_HLS/2024.1/tps/mingw/8.3.0/win64.o/nt\lib\gcc\x86_64-w64-mingw32\8.3.0\include\c++\array:190~../layer.h:42~../layer.h:260</SourceLocation>
<SummaryOfLoopViolations>
<VITIS_LOOP_40_1_VITIS_LOOP_41_2>
<Name>VITIS_LOOP_40_1_VITIS_LOOP_41_2</Name>
<IssueType>-</IssueType>
<ViolationType>-</ViolationType>
<SourceLocation>../layer.h:40~../layer.h:260</SourceLocation>
</VITIS_LOOP_40_1_VITIS_LOOP_41_2>
</SummaryOfLoopViolations>
</SummaryOfViolations>
</PerformanceEstimates>

<AreaEstimates>
<Resources>
<FF>17</FF>
<LUT>2307</LUT>
<BRAM_18K>0</BRAM_18K>
<DSP>0</DSP>
<URAM>0</URAM>
</Resources>
<AvailableResources>
<BRAM_18K>432</BRAM_18K>
<DSP>360</DSP>
<FF>141120</FF>
<LUT>70560</LUT>
<URAM>0</URAM>
</AvailableResources>
</AreaEstimates>

<InterfaceSummary>
<RtlPorts>
<name>ap_clk</name>
<Object>backProp&lt;64, 8, 8&gt;_Pipeline_VITIS_LOOP_40_1_VITIS_LOOP_41_2</Object>
<Type>return value</Type>
<Scope></Scope>
<IOProtocol>ap_ctrl_hs</IOProtocol>
<IOConfig></IOConfig>
<Dir>in</Dir>
<Bits>1</Bits>
<Attribute>control</Attribute>
</RtlPorts>
<RtlPorts>
<name>ap_rst</name>
<Object>backProp&lt;64, 8, 8&gt;_Pipeline_VITIS_LOOP_40_1_VITIS_LOOP_41_2</Object>
<Type>return value</Type>
<Scope></Scope>
<IOProtocol>ap_ctrl_hs</IOProtocol>
<IOConfig></IOConfig>
<Dir>in</Dir>
<Bits>1</Bits>
<Attribute>control</Attribute>
</RtlPorts>
<RtlPorts>
<name>ap_start</name>
<Object>backProp&lt;64, 8, 8&gt;_Pipeline_VITIS_LOOP_40_1_VITIS_LOOP_41_2</Object>
<Type>return value</Type>
<Scope></Scope>
<IOProtocol>ap_ctrl_hs</IOProtocol>
<IOConfig></IOConfig>
<Dir>in</Dir>
<Bits>1</Bits>
<Attribute>control</Attribute>
</RtlPorts>
<RtlPorts>
<name>ap_done</name>
<Object>backProp&lt;64, 8, 8&gt;_Pipeline_VITIS_LOOP_40_1_VITIS_LOOP_41_2</Object>
<Type>return value</Type>
<Scope></Scope>
<IOProtocol>ap_ctrl_hs</IOProtocol>
<IOConfig></IOConfig>
<Dir>out</Dir>
<Bits>1</Bits>
<Attribute>control</Attribute>
</RtlPorts>
<RtlPorts>
<name>ap_idle</name>
<Object>backProp&lt;64, 8, 8&gt;_Pipeline_VITIS_LOOP_40_1_VITIS_LOOP_41_2</Object>
<Type>return value</Type>
<Scope></Scope>
<IOProtocol>ap_ctrl_hs</IOProtocol>
<IOConfig></IOConfig>
<Dir>out</Dir>
<Bits>1</Bits>
<Attribute>control</Attribute>
</RtlPorts>
<RtlPorts>
<name>ap_ready</name>
<Object>backProp&lt;64, 8, 8&gt;_Pipeline_VITIS_LOOP_40_1_VITIS_LOOP_41_2</Object>
<Type>return value</Type>
<Scope></Scope>
<IOProtocol>ap_ctrl_hs</IOProtocol>
<IOConfig></IOConfig>
<Dir>out</Dir>
<Bits>1</Bits>
<Attribute>control</Attribute>
</RtlPorts>
<RtlPorts>
<name>w_l_plus1_T_77_address0</name>
<Object>w_l_plus1_T_77</Object>
<Type>array</Type>
<Scope></Scope>
<IOProtocol>ap_memory</IOProtocol>
<IOConfig></IOConfig>
<Dir>out</Dir>
<Bits>3</Bits>
<Attribute>address</Attribute>
</RtlPorts>
<RtlPorts>
<name>w_l_plus1_T_77_ce0</name>
<Object>w_l_plus1_T_77</Object>
<Type>array</Type>
<Scope></Scope>
<IOProtocol>ap_memory</IOProtocol>
<IOConfig></IOConfig>
<Dir>out</Dir>
<Bits>1</Bits>
<Attribute>control</Attribute>
</RtlPorts>
<RtlPorts>
<name>w_l_plus1_T_77_we0</name>
<Object>w_l_plus1_T_77</Object>
<Type>array</Type>
<Scope></Scope>
<IOProtocol>ap_memory</IOProtocol>
<IOConfig></IOConfig>
<Dir>out</Dir>
<Bits>1</Bits>
<Attribute>control</Attribute>
</RtlPorts>
<RtlPorts>
<name>w_l_plus1_T_77_d0</name>
<Object>w_l_plus1_T_77</Object>
<Type>array</Type>
<Scope></Scope>
<IOProtocol>ap_memory</IOProtocol>
<IOConfig></IOConfig>
<Dir>out</Dir>
<Bits>64</Bits>
<Attribute>data</Attribute>
</RtlPorts>
<RtlPorts>
<name>w_l_plus1_T_76_address0</name>
<Object>w_l_plus1_T_76</Object>
<Type>array</Type>
<Scope></Scope>
<IOProtocol>ap_memory</IOProtocol>
<IOConfig></IOConfig>
<Dir>out</Dir>
<Bits>3</Bits>
<Attribute>address</Attribute>
</RtlPorts>
<RtlPorts>
<name>w_l_plus1_T_76_ce0</name>
<Object>w_l_plus1_T_76</Object>
<Type>array</Type>
<Scope></Scope>
<IOProtocol>ap_memory</IOProtocol>
<IOConfig></IOConfig>
<Dir>out</Dir>
<Bits>1</Bits>
<Attribute>control</Attribute>
</RtlPorts>
<RtlPorts>
<name>w_l_plus1_T_76_we0</name>
<Object>w_l_plus1_T_76</Object>
<Type>array</Type>
<Scope></Scope>
<IOProtocol>ap_memory</IOProtocol>
<IOConfig></IOConfig>
<Dir>out</Dir>
<Bits>1</Bits>
<Attribute>control</Attribute>
</RtlPorts>
<RtlPorts>
<name>w_l_plus1_T_76_d0</name>
<Object>w_l_plus1_T_76</Object>
<Type>array</Type>
<Scope></Scope>
<IOProtocol>ap_memory</IOProtocol>
<IOConfig></IOConfig>
<Dir>out</Dir>
<Bits>64</Bits>
<Attribute>data</Attribute>
</RtlPorts>
<RtlPorts>
<name>w_l_plus1_T_75_address0</name>
<Object>w_l_plus1_T_75</Object>
<Type>array</Type>
<Scope></Scope>
<IOProtocol>ap_memory</IOProtocol>
<IOConfig></IOConfig>
<Dir>out</Dir>
<Bits>3</Bits>
<Attribute>address</Attribute>
</RtlPorts>
<RtlPorts>
<name>w_l_plus1_T_75_ce0</name>
<Object>w_l_plus1_T_75</Object>
<Type>array</Type>
<Scope></Scope>
<IOProtocol>ap_memory</IOProtocol>
<IOConfig></IOConfig>
<Dir>out</Dir>
<Bits>1</Bits>
<Attribute>control</Attribute>
</RtlPorts>
<RtlPorts>
<name>w_l_plus1_T_75_we0</name>
<Object>w_l_plus1_T_75</Object>
<Type>array</Type>
<Scope></Scope>
<IOProtocol>ap_memory</IOProtocol>
<IOConfig></IOConfig>
<Dir>out</Dir>
<Bits>1</Bits>
<Attribute>control</Attribute>
</RtlPorts>
<RtlPorts>
<name>w_l_plus1_T_75_d0</name>
<Object>w_l_plus1_T_75</Object>
<Type>array</Type>
<Scope></Scope>
<IOProtocol>ap_memory</IOProtocol>
<IOConfig></IOConfig>
<Dir>out</Dir>
<Bits>64</Bits>
<Attribute>data</Attribute>
</RtlPorts>
<RtlPorts>
<name>w_l_plus1_T_74_address0</name>
<Object>w_l_plus1_T_74</Object>
<Type>array</Type>
<Scope></Scope>
<IOProtocol>ap_memory</IOProtocol>
<IOConfig></IOConfig>
<Dir>out</Dir>
<Bits>3</Bits>
<Attribute>address</Attribute>
</RtlPorts>
<RtlPorts>
<name>w_l_plus1_T_74_ce0</name>
<Object>w_l_plus1_T_74</Object>
<Type>array</Type>
<Scope></Scope>
<IOProtocol>ap_memory</IOProtocol>
<IOConfig></IOConfig>
<Dir>out</Dir>
<Bits>1</Bits>
<Attribute>control</Attribute>
</RtlPorts>
<RtlPorts>
<name>w_l_plus1_T_74_we0</name>
<Object>w_l_plus1_T_74</Object>
<Type>array</Type>
<Scope></Scope>
<IOProtocol>ap_memory</IOProtocol>
<IOConfig></IOConfig>
<Dir>out</Dir>
<Bits>1</Bits>
<Attribute>control</Attribute>
</RtlPorts>
<RtlPorts>
<name>w_l_plus1_T_74_d0</name>
<Object>w_l_plus1_T_74</Object>
<Type>array</Type>
<Scope></Scope>
<IOProtocol>ap_memory</IOProtocol>
<IOConfig></IOConfig>
<Dir>out</Dir>
<Bits>64</Bits>
<Attribute>data</Attribute>
</RtlPorts>
<RtlPorts>
<name>w_l_plus1_T_73_address0</name>
<Object>w_l_plus1_T_73</Object>
<Type>array</Type>
<Scope></Scope>
<IOProtocol>ap_memory</IOProtocol>
<IOConfig></IOConfig>
<Dir>out</Dir>
<Bits>3</Bits>
<Attribute>address</Attribute>
</RtlPorts>
<RtlPorts>
<name>w_l_plus1_T_73_ce0</name>
<Object>w_l_plus1_T_73</Object>
<Type>array</Type>
<Scope></Scope>
<IOProtocol>ap_memory</IOProtocol>
<IOConfig></IOConfig>
<Dir>out</Dir>
<Bits>1</Bits>
<Attribute>control</Attribute>
</RtlPorts>
<RtlPorts>
<name>w_l_plus1_T_73_we0</name>
<Object>w_l_plus1_T_73</Object>
<Type>array</Type>
<Scope></Scope>
<IOProtocol>ap_memory</IOProtocol>
<IOConfig></IOConfig>
<Dir>out</Dir>
<Bits>1</Bits>
<Attribute>control</Attribute>
</RtlPorts>
<RtlPorts>
<name>w_l_plus1_T_73_d0</name>
<Object>w_l_plus1_T_73</Object>
<Type>array</Type>
<Scope></Scope>
<IOProtocol>ap_memory</IOProtocol>
<IOConfig></IOConfig>
<Dir>out</Dir>
<Bits>64</Bits>
<Attribute>data</Attribute>
</RtlPorts>
<RtlPorts>
<name>w_l_plus1_T_72_address0</name>
<Object>w_l_plus1_T_72</Object>
<Type>array</Type>
<Scope></Scope>
<IOProtocol>ap_memory</IOProtocol>
<IOConfig></IOConfig>
<Dir>out</Dir>
<Bits>3</Bits>
<Attribute>address</Attribute>
</RtlPorts>
<RtlPorts>
<name>w_l_plus1_T_72_ce0</name>
<Object>w_l_plus1_T_72</Object>
<Type>array</Type>
<Scope></Scope>
<IOProtocol>ap_memory</IOProtocol>
<IOConfig></IOConfig>
<Dir>out</Dir>
<Bits>1</Bits>
<Attribute>control</Attribute>
</RtlPorts>
<RtlPorts>
<name>w_l_plus1_T_72_we0</name>
<Object>w_l_plus1_T_72</Object>
<Type>array</Type>
<Scope></Scope>
<IOProtocol>ap_memory</IOProtocol>
<IOConfig></IOConfig>
<Dir>out</Dir>
<Bits>1</Bits>
<Attribute>control</Attribute>
</RtlPorts>
<RtlPorts>
<name>w_l_plus1_T_72_d0</name>
<Object>w_l_plus1_T_72</Object>
<Type>array</Type>
<Scope></Scope>
<IOProtocol>ap_memory</IOProtocol>
<IOConfig></IOConfig>
<Dir>out</Dir>
<Bits>64</Bits>
<Attribute>data</Attribute>
</RtlPorts>
<RtlPorts>
<name>w_l_plus1_T_71_address0</name>
<Object>w_l_plus1_T_71</Object>
<Type>array</Type>
<Scope></Scope>
<IOProtocol>ap_memory</IOProtocol>
<IOConfig></IOConfig>
<Dir>out</Dir>
<Bits>3</Bits>
<Attribute>address</Attribute>
</RtlPorts>
<RtlPorts>
<name>w_l_plus1_T_71_ce0</name>
<Object>w_l_plus1_T_71</Object>
<Type>array</Type>
<Scope></Scope>
<IOProtocol>ap_memory</IOProtocol>
<IOConfig></IOConfig>
<Dir>out</Dir>
<Bits>1</Bits>
<Attribute>control</Attribute>
</RtlPorts>
<RtlPorts>
<name>w_l_plus1_T_71_we0</name>
<Object>w_l_plus1_T_71</Object>
<Type>array</Type>
<Scope></Scope>
<IOProtocol>ap_memory</IOProtocol>
<IOConfig></IOConfig>
<Dir>out</Dir>
<Bits>1</Bits>
<Attribute>control</Attribute>
</RtlPorts>
<RtlPorts>
<name>w_l_plus1_T_71_d0</name>
<Object>w_l_plus1_T_71</Object>
<Type>array</Type>
<Scope></Scope>
<IOProtocol>ap_memory</IOProtocol>
<IOConfig></IOConfig>
<Dir>out</Dir>
<Bits>64</Bits>
<Attribute>data</Attribute>
</RtlPorts>
<RtlPorts>
<name>w_l_plus1_T_address0</name>
<Object>w_l_plus1_T</Object>
<Type>array</Type>
<Scope></Scope>
<IOProtocol>ap_memory</IOProtocol>
<IOConfig></IOConfig>
<Dir>out</Dir>
<Bits>3</Bits>
<Attribute>address</Attribute>
</RtlPorts>
<RtlPorts>
<name>w_l_plus1_T_ce0</name>
<Object>w_l_plus1_T</Object>
<Type>array</Type>
<Scope></Scope>
<IOProtocol>ap_memory</IOProtocol>
<IOConfig></IOConfig>
<Dir>out</Dir>
<Bits>1</Bits>
<Attribute>control</Attribute>
</RtlPorts>
<RtlPorts>
<name>w_l_plus1_T_we0</name>
<Object>w_l_plus1_T</Object>
<Type>array</Type>
<Scope></Scope>
<IOProtocol>ap_memory</IOProtocol>
<IOConfig></IOConfig>
<Dir>out</Dir>
<Bits>1</Bits>
<Attribute>control</Attribute>
</RtlPorts>
<RtlPorts>
<name>w_l_plus1_T_d0</name>
<Object>w_l_plus1_T</Object>
<Type>array</Type>
<Scope></Scope>
<IOProtocol>ap_memory</IOProtocol>
<IOConfig></IOConfig>
<Dir>out</Dir>
<Bits>64</Bits>
<Attribute>data</Attribute>
</RtlPorts>
<RtlPorts>
<name>w_l_plus1_val</name>
<Object>w_l_plus1_val</Object>
<Type>scalar</Type>
<Scope></Scope>
<IOProtocol>ap_none</IOProtocol>
<IOConfig></IOConfig>
<Dir>in</Dir>
<Bits>4096</Bits>
<Attribute>data</Attribute>
</RtlPorts>
</InterfaceSummary>

</profile>
